zangetsu_notification/__init__.py
zangetsu_notification/base.py
zangetsu_notification/email.py
zangetsu_notification/factory.py
zangetsu_notification/line.py
zangetsu_notification/slack.py
zangetsu_notification/teams.py
zangetsu_notification/webhook.py
zangetsu_notification-0.1.5.dist-info/METADATA
zangetsu_notification-0.1.5.dist-info/WHEEL
zangetsu_notification-0.1.5.dist-info/top_level.txt
zangetsu_notification-0.1.5.dist-info/RECORD
