Metadata-Version: 2.2
Name: zangetsu-notification
Version: 0.1.5
Summary: Add your description here
Requires-Python: >=3.11
Requires-Dist: requests>=2.32.3
